{
  "model": "MODEL_05_01_2026_02.vsp3",
  "analysis": "VSPAEROSweep_VLM",
  "mach": 0.15,
  "alpha_range_deg": [
    -4.0,
    16.0
  ],
  "polar": [
    {
      "alpha_deg": -4.0,
      "CL": -0.423783,
      "CD": 0.044367,
      "CM": 0.420724,
      "LD": -9.55
    },
    {
      "alpha_deg": -2.0,
      "CL": -0.243982,
      "CD": 0.026263,
      "CM": 0.235349,
      "LD": -9.29
    },
    {
      "alpha_deg": 0.0,
      "CL": -0.140816,
      "CD": 0.039665,
      "CM": 0.130535,
      "LD": -3.55
    },
    {
      "alpha_deg": 2.0,
      "CL": -0.061986,
      "CD": 0.023758,
      "CM": -0.001705,
      "LD": -2.61
    },
    {
      "alpha_deg": 4.0,
      "CL": 0.170474,
      "CD": 0.015659,
      "CM": -0.193403,
      "LD": 10.89
    },
    {
      "alpha_deg": 6.0,
      "CL": 0.43242,
      "CD": 0.017156,
      "CM": -0.467414,
      "LD": 25.21
    },
    {
      "alpha_deg": 8.0,
      "CL": 0.573382,
      "CD": 0.020767,
      "CM": -0.590453,
      "LD": 27.61
    },
    {
      "alpha_deg": 10.0,
      "CL": 0.730749,
      "CD": 0.031841,
      "CM": -0.752709,
      "LD": 22.95
    },
    {
      "alpha_deg": 12.0,
      "CL": 0.87493,
      "CD": 0.051195,
      "CM": -0.908092,
      "LD": 17.09
    },
    {
      "alpha_deg": 14.0,
      "CL": 1.036055,
      "CD": 0.0555,
      "CM": -1.056854,
      "LD": 18.67
    },
    {
      "alpha_deg": 16.0,
      "CL": 1.208913,
      "CD": 0.073639,
      "CM": -1.233393,
      "LD": 16.42
    }
  ],
  "CL_alpha_per_deg": 0.08327,
  "CL_0": -0.12177,
  "Cm_alpha_per_deg": -0.08388,
  "Cm_0": 0.10172,
  "CL_max_vlm": 1.2089,
  "vstall_est_ms": 17.66,
  "vstall_limit_ms": 18.0,
  "vstall_ok": true,
  "vcruise_75pct_ms": 57.97,
  "CL_cruise": 0.1122,
  "CD_cruise": 0.017688,
  "LD_cruise": 6.35,
  "longitudinal_stable": true,
  "Cm_alpha_sign": "negative (stable)"
}